skimage/_build.py
skimage/__init__.py
skimage/setup.py
skimage/conftest.py
skimage/exposure/__init__.py
skimage/exposure/setup.py
skimage/exposure/histogram_matching.py
skimage/exposure/_adapthist.py
skimage/exposure/exposure.py
skimage/exposure/tests/test_histogram_matching.py
skimage/exposure/tests/test_exposure.py
skimage/exposure/tests/__init__.py
skimage/data/motorcycle_left.png
skimage/data/camera.png
skimage/data/rocket.jpg
skimage/data/page.png
skimage/data/lfw_subset.npy
skimage/data/retina.jpg
skimage/data/gravel.png
skimage/data/microaneurysms.png
skimage/data/hubble_deep_field.jpg
skimage/data/chelsea.png
skimage/data/lbpcascade_frontalface_opencv.xml
skimage/data/_registry.py
skimage/data/chessboard_RGB.png
skimage/data/coffee.png
skimage/data/cell.png
skimage/data/__init__.py
skimage/data/color.png
skimage/data/coins.png
skimage/data/horse.png
skimage/data/_binary_blobs.py
skimage/data/phantom.png
skimage/data/motorcycle_disp.npz
skimage/data/clock_motion.png
skimage/data/grass.png
skimage/data/setup.py
skimage/data/brick.png
skimage/data/motorcycle_right.png
skimage/data/moon.png
skimage/data/ihc.png
skimage/data/chessboard_GRAY.png
skimage/data/README.txt
skimage/data/logo.png
skimage/data/text.png
skimage/data/astronaut.png
skimage/data/tests/__init__.py
skimage/data/tests/test_data.py
skimage/util/_remap.cpython-36m-aarch64-linux-gnu.so
skimage/util/unique.py
skimage/util/_map_array.py
skimage/util/noise.py
skimage/util/apply_parallel.py
skimage/util/lookfor.py
skimage/util/shape.py
skimage/util/arraycrop.py
skimage/util/__init__.py
skimage/util/dtype.py
skimage/util/setup.py
skimage/util/_montage.py
skimage/util/compare.py
skimage/util/_invert.py
skimage/util/_regular_grid.py
skimage/util/tests/test_arraycrop.py
skimage/util/tests/test_shape.py
skimage/util/tests/test_arraypad.py
skimage/util/tests/test_dtype.py
skimage/util/tests/test_regular_grid.py
scikit_image_arm64-0.17.2.dist-info/entry_points.txt
scikit_image_arm64-0.17.2.dist-info/WHEEL
scikit_image_arm64-0.17.2.dist-info/RECORD
scikit_image_arm64-0.17.2.dist-info/METADATA
scikit_image_arm64-0.17.2.dist-info/LICENSE.txt
scikit_image_arm64-0.17.2.dist-info/top_level.txt
