Metadata-Version: 2.1
Name: scikit-image-arm64
Version: 0.17.2
Summary: Image processing in Python
Home-page: https://scikit-image.org
Maintainer: Stefan van der Walt
Maintainer-email: stefan@sun.ac.za
License: Modified BSD
Download-URL: https://scikit-image.org/docs/stable/install.html
Project-URL: Bug Tracker, https://github.com/scikit-image/scikit-image/issues
Project-URL: Documentation, https://scikit-image.org/docs/stable/
Project-URL: Source Code, https://github.com/scikit-image/scikit-image
Platform: UNKNOWN
Classifier: Development Status :: 4 - Beta
Classifier: Environment :: Console
Classifier: Intended Audience :: Developers
Classifier: Intended Audience :: Science/Research
Classifier: License :: OSI Approved :: BSD License
Classifier: Programming Language :: C
Classifier: Programming Language :: Python
Classifier: Programming Language :: Python :: 3
Classifier: Programming Language :: Python :: 3.6
Classifier: Programming Language :: Python :: 3.7
Classifier: Programming Language :: Python :: 3 :: Only
Classifier: Topic :: Scientific/Engineering
Classifier: Operating System :: Microsoft :: Windows
Classifier: Operating System :: POSIX
Classifier: Operating System :: Unix
Classifier: Operating System :: MacOS
Requires: numpy (>= 1.15.1)
Requires: scipy (>= 1.0.1)
Requires: matplotlib (>= 2.0.0,!=3.0.0)
Requires: networkx (>= 2.0)
Requires: pillow (>= 4.3.0,!=7.1.0,!=7.1.1)
Requires: imageio (>= 2.3.0)
Requires: tifffile (>= 2019.7.26)
Requires: PyWavelets (>= 1.1.1)
Requires-Python: >=3.6
License-File: LICENSE.txt
Requires-Dist: numpy (>=1.15.1)
Requires-Dist: scipy (>=1.0.1)
Requires-Dist: matplotlib (!=3.0.0,>=2.0.0)
Requires-Dist: networkx (>=2.0)
Requires-Dist: pillow (!=7.1.0,!=7.1.1,>=4.3.0)
Requires-Dist: imageio (>=2.3.0)
Requires-Dist: tifffile (>=2019.7.26)
Requires-Dist: PyWavelets (>=1.1.1)
Provides-Extra: docs
Requires-Dist: sphinx (<=2.4.4,>=1.8) ; extra == 'docs'
Requires-Dist: numpydoc (>=0.9) ; extra == 'docs'
Requires-Dist: sphinx-gallery (>=0.3.1) ; extra == 'docs'
Requires-Dist: sphinx-copybutton ; extra == 'docs'
Requires-Dist: pytest-runner ; extra == 'docs'
Requires-Dist: scikit-learn ; extra == 'docs'
Requires-Dist: matplotlib (>=3.0.1) ; extra == 'docs'
Requires-Dist: dask[array] (>=0.15.0) ; extra == 'docs'
Requires-Dist: cloudpickle (>=0.2.1) ; extra == 'docs'
Requires-Dist: pandas (>=0.23.0) ; extra == 'docs'
Requires-Dist: seaborn (>=0.7.1) ; extra == 'docs'
Requires-Dist: pooch (>=0.5.2) ; extra == 'docs'
Provides-Extra: optional
Requires-Dist: SimpleITK ; extra == 'optional'
Requires-Dist: astropy (>=1.2.0) ; extra == 'optional'
Requires-Dist: qtpy ; extra == 'optional'
Requires-Dist: pyamg ; extra == 'optional'
Requires-Dist: dask[array] (>=0.15.0) ; extra == 'optional'
Requires-Dist: cloudpickle (>=0.2.1) ; extra == 'optional'
Requires-Dist: pooch (>=0.5.2) ; extra == 'optional'
Provides-Extra: test
Requires-Dist: pytest (!=3.7.3) ; extra == 'test'
Requires-Dist: pytest-cov ; extra == 'test'
Requires-Dist: pytest-localserver ; extra == 'test'
Requires-Dist: flake8 ; extra == 'test'
Requires-Dist: codecov ; extra == 'test'
